configPy/__init__.py
configPy/jsonConfigParser.py
configPy/ndjsonConfigParser.py
configPy/txtConfigParser.py
tests/JSONConfigParser_test.py
tests/NDJSONConfigParser_test.py
tests/__init__.py
configParsePy-0.1.dist-info/LICENSE
configParsePy-0.1.dist-info/METADATA
configParsePy-0.1.dist-info/WHEEL
configParsePy-0.1.dist-info/top_level.txt
configParsePy-0.1.dist-info/RECORD
