Metadata-Version: 2.1
Name: configParsePy
Version: 0.1
Summary: A tiny Configuration File Parser for Python Projects. Currently Supports JSON files only.
Home-page: https://github.com/TanmoySG/configPy
Author: Tanmoy Sen Gupta
Author-email: tanmoysps@gmail.com
License: MIT
Keywords: imports,configurations,python,project
Platform: UNKNOWN
Classifier: Programming Language :: Python :: 3
Classifier: License :: OSI Approved :: MIT License
Classifier: Operating System :: OS Independent
License-File: LICENSE
